[{"operationId":"LM9iI2Q1m0elkAn9fno0sA","operationType":"callMicroflow","parameters":{"EmailMessage":["Email_Connector.EmailMessage"]},"constants":{"MicroflowName":"Email_Connector.ACT_EmailMessage_SendComposedEmail"},"allowedUserRoleSets":[["Administrator"],["Manager"]]},{"operationId":"ApyM1xA2u0eRp1faRlcwkw","operationType":"delete","parameters":{"Objects":["[UserManagement.User]"]},"constants":{},"allowedUserRoleSets":[["Administrator"],["User"],["Manager"]]},{"operationId":"LtMB2o/v6EanDWlI1tbYLg","operationType":"callMicroflow","parameters":{"EmailTemplate":["Email_Connector.EmailTemplate"]},"constants":{"MicroflowName":"Email_Connector.OCH_EmailTemplate_ToggleRecipients"},"allowedUserRoleSets":[["Administrator"],["Manager"]]},{"operationId":"Dwaz+kDxP0W0wZGwwxAfSA","operationType":"rollback","parameters":{"Objects":["AnyObjectList"]},"constants":{},"allowedUserRoleSets":[["Administrator"],["User"],["Manager"],["Guest"]]},{"operationId":"hwO2+fBPqEyhjHF05qQDeA","operationType":"callMicroflow","parameters":{},"constants":{"MicroflowName":"Main.ACT_GetUser"},"allowedUserRoleSets":[["Administrator"],["User"],["Manager"],["Guest"]]},{"operationId":"BHLSLlQJjUufMdvg/sNClw","operationType":"callMicroflow","parameters":{"EmailMessage":["Email_Connector.EmailMessage"]},"constants":{"MicroflowName":"Email_Connector.VAL_Pk12Certificate"},"allowedUserRoleSets":[["Administrator"],["User"],["Manager"],["Guest"]]},{"operationId":"QxqHDJA4QUCy4v6nxwy3UA","operationType":"callMicroflow","parameters":{"EmailMessage":["Email_Connector.EmailMessage"]},"constants":{"MicroflowName":"Email_Connector.OCH_EmailMessage_ToggleRecipients"},"allowedUserRoleSets":[["Administrator"],["Manager"]]},{"operationId":"k8hPWQOhhEq9bCt7x6HtOg","operationType":"callMicroflow","parameters":{"Selection":["MxModelReflection.MxObjectReference"],"MxObjectType":["MxModelReflection.MxObjectType"]},"constants":{"MicroflowName":"MxModelReflection.IVK_OpenReferencedMendixObject"},"allowedUserRoleSets":[["Administrator"],["Manager"]]},{"operationId":"M15jfLTJDUCi2EDDtg9yNQ","operationType":"commit","parameters":{"Objects":["AnyObjectList"]},"constants":{},"allowedUserRoleSets":[["Administrator"],["User"],["Manager"],["Guest"]]},{"operationId":"Lr3cIOZ4Bk+kzOBp4rpeYg","operationType":"callMicroflow","parameters":{"IncomingServer":["Email_Connector.IncomingServer"]},"constants":{"MicroflowName":"Email_Connector.OEN_SetIncomingServer"},"allowedUserRoleSets":[["Administrator"],["User"],["Manager"],["Guest"]]},{"operationId":"OC5YcIlDd061JwY0RnZr+w","operationType":"rollback","parameters":{"Objects":["AnyObjectList"]},"constants":{},"allowedUserRoleSets":[["Administrator"],["User"],["Manager"],["Guest"]]},{"operationId":"0TXt+chEe06zGTr2dzh1lg","operationType":"rollback","parameters":{"Objects":["AnyObjectList"]},"constants":{},"allowedUserRoleSets":[["Administrator"],["User"],["Manager"],["Guest"]]},{"operationId":"N0SxoxOOakWhrfh4vr5myw","operationType":"rollback","parameters":{"Objects":["AnyObjectList"]},"constants":{},"allowedUserRoleSets":[["Administrator"],["User"],["Manager"],["Guest"]]},{"operationId":"OyKzSubdmk2dZ5x8Y+4o1Q","operationType":"callMicroflow","parameters":{"Token":["MxModelReflection.Token"]},"constants":{"MicroflowName":"MxModelReflection.Ch_FindReference"},"allowedUserRoleSets":[["Administrator"],["User"],["Manager"],["Guest"]]},{"operationId":"ZYV4Qe4KGUe9Xzibrp5pOw","operationType":"callMicroflow","parameters":{"Token":["MxModelReflection.Token"]},"constants":{"MicroflowName":"MxModelReflection.Ch_ObjecttypeReference"},"allowedUserRoleSets":[["Administrator"],["User"],["Manager"],["Guest"]]},{"operationId":"u2UdD1K0YkWBLiWJhiBRSg","operationType":"rollback","parameters":{"Objects":["AnyObjectList"]},"constants":{},"allowedUserRoleSets":[["Administrator"],["User"],["Manager"],["Guest"]]},{"operationId":"RnfbqZk2sk29UT9yhBMDtw","operationType":"rollback","parameters":{"Objects":["AnyObjectList"]},"constants":{},"allowedUserRoleSets":[["Administrator"],["User"],["Manager"],["Guest"]]},{"operationId":"pm6VG/f9lEm5RpKAy2S6Qw","operationType":"callMicroflow","parameters":{"PasswordData":["Encryption.PasswordData"]},"constants":{"MicroflowName":"Encryption.MB_ChangePasswordSave"},"allowedUserRoleSets":[]},{"operationId":"EJKbg7EEMU2JzL890FOpHg","operationType":"callMicroflow","parameters":{"Registration":["UserManagement.Registration"]},"constants":{"MicroflowName":"UserManagement.ACT_Registration_CreateTeamMember"},"allowedUserRoleSets":[["Guest"]]},{"operationId":"D0Nt87T+MU6UuxFWDTqC4w","operationType":"rollback","parameters":{"Objects":["AnyObjectList"]},"constants":{},"allowedUserRoleSets":[["Administrator"],["User"],["Manager"],["Guest"]]},{"operationId":"SJma1ZAAIUK1DH8z/NUM6Q","operationType":"callMicroflow","parameters":{"MxObjectType":["MxModelReflection.MxObjectType"]},"constants":{"MicroflowName":"MxModelReflection.DSO_InheritsFromContainer"},"allowedUserRoleSets":[["Administrator"],["User"],["Manager"],["Guest"]]},{"operationId":"urYC6f4lGEm9J+PQSvuk9Q","operationType":"rollback","parameters":{"Objects":["AnyObjectList"]},"constants":{},"allowedUserRoleSets":[["Administrator"],["User"],["Manager"],["Guest"]]},{"operationId":"eDLeWpV+4kaNKXlZ/tV2jQ","operationType":"callMicroflow","parameters":{},"constants":{"MicroflowName":"AdministrationManagement.DS_Registration_Get"},"allowedUserRoleSets":[["Administrator"],["User"],["Manager"],["Guest"]]},{"operationId":"iZ6Hkb8S+kKTILjO2I5y4Q","operationType":"callMicroflow","parameters":{"EmailMessage":["Email_Connector.EmailMessage"]},"constants":{"MicroflowName":"Email_Connector.OCH_EmailMessage_ToggleRecipients"},"allowedUserRoleSets":[["Administrator"],["Manager"]]},{"operationId":"wmMWG71W5kCFLvDo9+yJhA","operationType":"callMicroflow","parameters":{"EmailAccount":["Email_Connector.EmailAccount"]},"constants":{"MicroflowName":"Email_Connector.DS_GetLDAPConfiguration"},"allowedUserRoleSets":[["Administrator"],["User"],["Manager"],["Guest"]]},{"operationId":"pd7F6QPvlka7zt3uZ3ym1Q","operationType":"rollback","parameters":{"Objects":["AnyObjectList"]},"constants":{},"allowedUserRoleSets":[["Administrator"],["User"],["Manager"],["Guest"]]},{"operationId":"85+A9AP2BE+WvXouJD1mog","operationType":"callMicroflow","parameters":{"LDAPBaseName":["Email_Connector.LDAPBaseDN"],"LDAPConfiguration":["Email_Connector.LDAPConfiguration"]},"constants":{"MicroflowName":"Email_Connector.ACT_LDAPConfiguration_ChangeBaseName"},"allowedUserRoleSets":[["Administrator"],["Manager"]]},{"operationId":"RpeJBgNdlUuUOach7xuiAg","operationType":"callMicroflow","parameters":{"Room":["Rooms.Room"]},"constants":{"MicroflowName":"Rooms.DS_Booking_Events"},"allowedUserRoleSets":[["Administrator"],["User"],["Manager"],["Guest"]]},{"operationId":"ak0R2qN0o0CdZJdNFyV0mw","operationType":"callMicroflow","parameters":{"OAuthProvider":["Email_Connector.OAuthProvider"]},"constants":{"MicroflowName":"Email_Connector.ACT_OAuthProvider_ShowOAuthProviderPage"},"allowedUserRoleSets":[["Administrator"],["Manager"]]},{"operationId":"k8G+PZo+W0yNyeWt9KMErw","operationType":"callMicroflow","parameters":{"Attachment":["Email_Connector.Attachment"]},"constants":{"MicroflowName":"Email_Connector.ACT_Attachment_Download"},"allowedUserRoleSets":[["Administrator"],["Manager"]]},{"operationId":"+3++16E4Jk+tgtvcXD9Tgg","operationType":"rollback","parameters":{"Objects":["AnyObjectList"]},"constants":{},"allowedUserRoleSets":[["Administrator"],["User"],["Manager"],["Guest"]]},{"operationId":"V3daulHG8UKnX8w8abdh7Q","operationType":"callMicroflow","parameters":{"Certificate":["Encryption.PGPCertificate"]},"constants":{"MicroflowName":"Encryption.MB_SaveCertificate"},"allowedUserRoleSets":[]},{"operationId":"x7+muJqY/0uqX+uc7QMbzg","operationType":"delete","parameters":{"Objects":["[Rooms.Room]"]},"constants":{},"allowedUserRoleSets":[["Administrator"],["Manager"]]},{"operationId":"ei2AHq4tDUKR+wwmDKCHXQ","operationType":"commit","parameters":{"Objects":["AnyObjectList"]},"constants":{},"allowedUserRoleSets":[["Administrator"],["User"],["Manager"],["Guest"]]},{"operationId":"ueOhDoooI0O5rSkZ3S5fsA","operationType":"callMicroflow","parameters":{},"constants":{"MicroflowName":"RESTConsume.CreateInput"},"allowedUserRoleSets":[["Administrator"],["User"],["Manager"],["Guest"]]},{"operationId":"iu36JfrNc0+JbfMQxlr3LA","operationType":"callMicroflow","parameters":{"EmailTemplate":["Email_Connector.EmailTemplate"]},"constants":{"MicroflowName":"Email_Connector.ACT_EmailTemplate_DuplicateAndShowPage"},"allowedUserRoleSets":[["Administrator"],["Manager"]]},{"operationId":"dR33MMou1UW9/l3DC4HlPw","operationType":"callMicroflow","parameters":{},"constants":{"MicroflowName":"Administration.RetrieveTimeZones"},"allowedUserRoleSets":[["Administrator"],["User"],["Manager"],["Guest"]]},{"operationId":"fyQqPLsrFUOU3DwavwwSTw","operationType":"rollback","parameters":{"Objects":["AnyObjectList"]},"constants":{},"allowedUserRoleSets":[["Administrator"],["User"],["Manager"],["Guest"]]},{"operationId":"Dft3ndi3jkeR9syEbkGXLQ","operationType":"create","parameters":{},"constants":{"ObjectType":"Encryption.ExampleConfiguration"},"allowedUserRoleSets":[]},{"operationId":"dxeYoByd1UWwUzoRNeFD/w","operationType":"rollback","parameters":{"Objects":["AnyObjectList"]},"constants":{},"allowedUserRoleSets":[["Administrator"],["User"],["Manager"],["Guest"]]},{"operationId":"gAoUIF8ZEU2S3PouN6/rSQ","operationType":"callMicroflow","parameters":{},"constants":{"MicroflowName":"System.ShowHomePage"},"allowedUserRoleSets":[["Administrator"],["User"],["Manager"],["Guest"]]},{"operationId":"Lky+BbeJoESWiC4WI9vYzw","operationType":"callMicroflow","parameters":{"EmailAccount":["Email_Connector.EmailAccount"]},"constants":{"MicroflowName":"Email_Connector.SUB_EmailAccount_Save"},"allowedUserRoleSets":[["Administrator"],["Manager"]]},{"operationId":"TNoOHsOgeUGfgmy6CGrZmw","operationType":"create","parameters":{},"constants":{"ObjectType":"Rooms.Equipment"},"allowedUserRoleSets":[["Administrator"],["Manager"]]},{"operationId":"R+BSkNiv0k2S6Ekqz6QdGA","operationType":"callMicroflow","parameters":{"EmailMessage":["Email_Connector.EmailMessage"]},"constants":{"MicroflowName":"Email_Connector.ACT_EmailMessage_SendEmailAndClosePage"},"allowedUserRoleSets":[["Administrator"],["Manager"]]},{"operationId":"1HuJknf0GEKVKgfAarDCPg","operationType":"callMicroflow","parameters":{"EmailAccount":["Email_Connector.EmailAccount"]},"constants":{"MicroflowName":"Email_Connector.ACT_EmailAccount_SaveManualConfig"},"allowedUserRoleSets":[["Administrator"],["Manager"]]},{"operationId":"a/lRJLxciU+IsmfRjQkQjA","operationType":"callMicroflow","parameters":{"Booking":["CalendarEvents.Booking"],"Room":["Rooms.Room"]},"constants":{"MicroflowName":"CalendarEvents.ACT_Booking_Save"},"allowedUserRoleSets":[["Administrator"],["User"],["Manager"]]},{"operationId":"4MsEMlZH7UymjN1xqm2y3w","operationType":"rollback","parameters":{"Objects":["AnyObjectList"]},"constants":{},"allowedUserRoleSets":[["Administrator"],["User"],["Manager"],["Guest"]]},{"operationId":"+9PwCnU8GUC4IUB7h0qRGA","operationType":"delete","parameters":{"Objects":["[Encryption.ExampleConfiguration]"]},"constants":{},"allowedUserRoleSets":[]},{"operationId":"e8mbSfrSN0Kigzh6ZY52UQ","operationType":"callMicroflow","parameters":{"Token":["MxModelReflection.Token"]},"constants":{"MicroflowName":"MxModelReflection.Ch_FindMember"},"allowedUserRoleSets":[["Administrator"],["User"],["Manager"],["Guest"]]},{"operationId":"7F9XN5t0r0O4iospa1zYGA","operationType":"rollback","parameters":{"Objects":["AnyObjectList"]},"constants":{},"allowedUserRoleSets":[["Administrator"],["User"],["Manager"],["Guest"]]},{"operationId":"tSwkuYZpF0eOcEaeQMobPw","operationType":"callMicroflow","parameters":{"EmailAccount":["Email_Connector.EmailAccount"]},"constants":{"MicroflowName":"Email_Connector.ACT_EmailAccount_SaveEmailSecurityConfiguration"},"allowedUserRoleSets":[["Administrator"],["Manager"]]},{"operationId":"ITCIG4sUqUiNkoi1MzUz9A","operationType":"rollback","parameters":{"Objects":["AnyObjectList"]},"constants":{},"allowedUserRoleSets":[["Administrator"],["User"],["Manager"],["Guest"]]},{"operationId":"6VPw+WdrAUmlhew2psZjQQ","operationType":"rollback","parameters":{"Objects":["AnyObjectList"]},"constants":{},"allowedUserRoleSets":[["Administrator"],["User"],["Manager"],["Guest"]]},{"operationId":"zZkTnNQMj0SeunkzsT7oUA","operationType":"callMicroflow","parameters":{"EmailAccount":["Email_Connector.EmailAccount"]},"constants":{"MicroflowName":"Email_Connector.OCH_LDAPConfiguration_DeleteConfiguration"},"allowedUserRoleSets":[["Administrator"],["User"],["Manager"],["Guest"]]},{"operationId":"1vnCBWpVukyUAZ5QTMGHwg","operationType":"callMicroflow","parameters":{},"constants":{"MicroflowName":"Encryption.MB_NewPubKey"},"allowedUserRoleSets":[]},{"operationId":"M+9MdxJSq02VQpdbwePxeA","operationType":"callMicroflow","parameters":{},"constants":{"MicroflowName":"Email_Connector.ACT_ShowAccountLoginPage"},"allowedUserRoleSets":[["Administrator"],["Manager"]]},{"operationId":"1ll6vPq8TUG46i3yn0OgoQ","operationType":"delete","parameters":{"Objects":["[Email_Connector.EmailMessage]"]},"constants":{},"allowedUserRoleSets":[["Administrator"],["Manager"]]},{"operationId":"zWPsHuRwFkKnSIcXxFIGBg","operationType":"delete","parameters":{"Objects":["[MxModelReflection.DbSizeEstimate]"]},"constants":{},"allowedUserRoleSets":[]},{"operationId":"ST78NEM/Yk+bB8ptychxcg","operationType":"callMicroflow","parameters":{"EmailAccount":["Email_Connector.EmailAccount"]},"constants":{"MicroflowName":"Email_Connector.OCH_LDAPConfiguration_DeleteConfiguration"},"allowedUserRoleSets":[["Administrator"],["User"],["Manager"],["Guest"]]},{"operationId":"f0jlzhzH8EmbnkcyumhdjQ","operationType":"callMicroflow","parameters":{"EmailMessage":["Email_Connector.EmailMessage"]},"constants":{"MicroflowName":"Email_Connector.ACT_Attachment_CreateNew"},"allowedUserRoleSets":[["Administrator"],["Manager"]]},{"operationId":"pld5CBihI0moqW8NMT7t0g","operationType":"callMicroflow","parameters":{},"constants":{"MicroflowName":"Encryption.MB_GenerateKeyShowPage"},"allowedUserRoleSets":[]},{"operationId":"jniU+RTOwkyw3/Oem68ghg","operationType":"callMicroflow","parameters":{"Token":["MxModelReflection.Token"]},"constants":{"MicroflowName":"MxModelReflection.Ch_Member"},"allowedUserRoleSets":[["Administrator"],["User"],["Manager"],["Guest"]]},{"operationId":"zozvzELJ3kWwFqibd7pRmw","operationType":"callMicroflow","parameters":{"EmailAccount":["Email_Connector.EmailAccount"]},"constants":{"MicroflowName":"Email_Connector.ACT_EmailAccount_SaveEmailSecurityConfiguration"},"allowedUserRoleSets":[["Administrator"],["Manager"]]},{"operationId":"BToU0Ika10GhSmDGne/U/g","operationType":"rollback","parameters":{"Objects":["AnyObjectList"]},"constants":{},"allowedUserRoleSets":[["Administrator"],["User"],["Manager"],["Guest"]]},{"operationId":"Z8L84EMjw0qUuAS8m7PiVg","operationType":"callMicroflow","parameters":{"Certificate":["Encryption.PGPCertificate"]},"constants":{"MicroflowName":"Encryption.MB_SaveCertificate"},"allowedUserRoleSets":[]},{"operationId":"uAol/vx+kUCeOyDjq/r17w","operationType":"rollback","parameters":{"Objects":["AnyObjectList"]},"constants":{},"allowedUserRoleSets":[["Administrator"],["User"],["Manager"],["Guest"]]},{"operationId":"4PLWD/YEMEOXak57pogpmw","operationType":"callMicroflow","parameters":{"IncomingEmailConfiguration":["Email_Connector.IncomingEmailConfiguration"]},"constants":{"MicroflowName":"Email_Connector.DS_FolderList"},"allowedUserRoleSets":[["Administrator"],["User"],["Manager"],["Guest"]]},{"operationId":"jC9jgBRLdU2oO749MeUo9Q","operationType":"commit","parameters":{"Objects":["AnyObjectList"]},"constants":{},"allowedUserRoleSets":[["Administrator"],["User"],["Manager"],["Guest"]]},{"operationId":"3OzueAxaK0uPGpO0PjJnwg","operationType":"callMicroflow","parameters":{"Attachment":["Email_Connector.Attachment"]},"constants":{"MicroflowName":"Email_Connector.ACT_Attachment_Download"},"allowedUserRoleSets":[["Administrator"],["Manager"]]},{"operationId":"IyHkvnLNL0WaYDD2sLD/Lg","operationType":"callMicroflow","parameters":{"OAuthProvider":["Email_Connector.OAuthProvider"]},"constants":{"MicroflowName":"Email_Connector.ACT_OAuthProvider_Save"},"allowedUserRoleSets":[["Administrator"],["Manager"]]},{"operationId":"WaC+I9PkHUiLwm7Ea9XIOg","operationType":"rollback","parameters":{"Objects":["AnyObjectList"]},"constants":{},"allowedUserRoleSets":[["Administrator"],["User"],["Manager"],["Guest"]]},{"operationId":"xNwY0uAIC02uGG/O1yAZ1Q","operationType":"callMicroflow","parameters":{"EmailAccount":["Email_Connector.EmailAccount"]},"constants":{"MicroflowName":"Email_Connector.ACT_ShowAccountSettingsPage"},"allowedUserRoleSets":[["Administrator"],["Manager"]]},{"operationId":"R0d1Xfd3yEyfc0uSJ0Qplw","operationType":"callMicroflow","parameters":{"EmailAccount":["Email_Connector.EmailAccount"]},"constants":{"MicroflowName":"Email_Connector.OCH_Pk12Certificate_DeleteCertificate"},"allowedUserRoleSets":[["Administrator"],["User"],["Manager"],["Guest"]]},{"operationId":"l97BYd0pdkq3uQBm/oNVMQ","operationType":"rollback","parameters":{"Objects":["AnyObjectList"]},"constants":{},"allowedUserRoleSets":[["Administrator"],["User"],["Manager"],["Guest"]]},{"operationId":"UiTu1V8D+kOdmtNs9NDGEQ","operationType":"callMicroflow","parameters":{"Certificate_PrivateKey":["Encryption.PGPCertificate"]},"constants":{"MicroflowName":"Encryption.MB_GenerateCertificate"},"allowedUserRoleSets":[]},{"operationId":"Efw5OpNweEe7Jhh24wV1WA","operationType":"rollback","parameters":{"Objects":["AnyObjectList"]},"constants":{},"allowedUserRoleSets":[["Administrator"],["User"],["Manager"],["Guest"]]},{"operationId":"xJm0dS17BEe3X3U6y2LyiQ","operationType":"callMicroflow","parameters":{},"constants":{"MicroflowName":"Email_Connector.ACT_EmailAccount_LaunchEmailConnectorOverview"},"allowedUserRoleSets":[["Administrator"],["Manager"]]},{"operationId":"zsnt15g1QkeFLHOIXojwdw","operationType":"rollback","parameters":{"Objects":["AnyObjectList"]},"constants":{},"allowedUserRoleSets":[["Administrator"],["User"],["Manager"],["Guest"]]},{"operationId":"Y5FNlg/5Y0OiJZglO9pTEg","operationType":"rollback","parameters":{"Objects":["AnyObjectList"]},"constants":{},"allowedUserRoleSets":[["Administrator"],["User"],["Manager"],["Guest"]]},{"operationId":"hFfQvcZG6UWkxfOPKRPi2g","operationType":"rollback","parameters":{"Objects":["AnyObjectList"]},"constants":{},"allowedUserRoleSets":[["Administrator"],["User"],["Manager"],["Guest"]]},{"operationId":"e17QnQB7uEqBxBfD2Thtwg","operationType":"rollback","parameters":{"Objects":["AnyObjectList"]},"constants":{},"allowedUserRoleSets":[["Administrator"],["User"],["Manager"],["Guest"]]},{"operationId":"gwm1SMYGTE+RhfEw1OAGsg","operationType":"callMicroflow","parameters":{"Account":["Administration.Account"]},"constants":{"MicroflowName":"Administration.ShowMyPasswordForm"},"allowedUserRoleSets":[["Administrator"],["User"],["Manager"]]},{"operationId":"tVvA+99IuUiayKzwywJ9YA","operationType":"rollback","parameters":{"Objects":["AnyObjectList"]},"constants":{},"allowedUserRoleSets":[["Administrator"],["User"],["Manager"],["Guest"]]},{"operationId":"YwwLf02n/U69zbZOcp2QHA","operationType":"callMicroflow","parameters":{"Account":["Administration.Account"]},"constants":{"MicroflowName":"Administration.ShowPasswordForm"},"allowedUserRoleSets":[["Administrator"],["Manager"]]},{"operationId":"A0bmyVe4JUeSa0bQcBtMqA","operationType":"rollback","parameters":{"Objects":["AnyObjectList"]},"constants":{},"allowedUserRoleSets":[["Administrator"],["User"],["Manager"],["Guest"]]},{"operationId":"U/zzpHk6JUiX6A1/46HaTw","operationType":"rollback","parameters":{"Objects":["AnyObjectList"]},"constants":{},"allowedUserRoleSets":[["Administrator"],["User"],["Manager"],["Guest"]]},{"operationId":"v9rR4MfyTk6QHgGlxL3deA","operationType":"callMicroflow","parameters":{"OAuthProvider":["Email_Connector.OAuthProvider"]},"constants":{"MicroflowName":"Email_Connector.ACT_OAuthProvider_ShowOAuthProviderPage"},"allowedUserRoleSets":[["Administrator"],["Manager"]]},{"operationId":"+SuAGeI53E24hV24Ywxe2Q","operationType":"callMicroflow","parameters":{"Token":["MxModelReflection.Token"]},"constants":{"MicroflowName":"MxModelReflection.Ch_FindMemberReference"},"allowedUserRoleSets":[["Administrator"],["User"],["Manager"],["Guest"]]},{"operationId":"UMTlt9UTI0OBg6Dm6aBd4g","operationType":"callMicroflow","parameters":{"EmailMessage":["Email_Connector.EmailMessage"]},"constants":{"MicroflowName":"Email_Connector.ACT_EmailMessage_Delete"},"allowedUserRoleSets":[["Administrator"],["Manager"]]},{"operationId":"ez+zenLaa0OCgF0U6FIV2A","operationType":"rollback","parameters":{"Objects":["AnyObjectList"]},"constants":{},"allowedUserRoleSets":[["Administrator"],["User"],["Manager"],["Guest"]]},{"operationId":"2rj4Em8IhkSBtuPTxOHkaA","operationType":"callMicroflow","parameters":{"EmailTemplate":["Email_Connector.EmailTemplate"]},"constants":{"MicroflowName":"Email_Connector.ACT_Emailtemplate_CreateToken"},"allowedUserRoleSets":[["Administrator"],["Manager"]]},{"operationId":"TLdYvCAeUUeSVz5Qy7QTiA","operationType":"callMicroflow","parameters":{"EmailTemplate":["Email_Connector.EmailTemplate"]},"constants":{"MicroflowName":"Email_Connector.ACT_EmailTemplate_GenerateAndSetPlainText"},"allowedUserRoleSets":[["Administrator"],["Manager"]]},{"operationId":"xSTGoA3k+kCAWVSMOCQISw","operationType":"callMicroflow","parameters":{},"constants":{"MicroflowName":"Rooms.ACT_Room_Create"},"allowedUserRoleSets":[["Administrator"],["Manager"]]},{"operationId":"9dnkFCXJNkKGFK1/Xur1MQ","operationType":"callMicroflow","parameters":{"Folder":["Email_Connector.Folder"],"IncomingEmailConfiguration":["Email_Connector.IncomingEmailConfiguration"]},"constants":{"MicroflowName":"Email_Connector.ACT_IncomingEmailConfiguration_FolderSelect"},"allowedUserRoleSets":[["Administrator"],["Manager"]]},{"operationId":"9w7dHzzrmUyDjwDWS01JYA","operationType":"rollback","parameters":{"Objects":["AnyObjectList"]},"constants":{},"allowedUserRoleSets":[["Administrator"],["User"],["Manager"],["Guest"]]},{"operationId":"G+mCSwjGEEusuI5Xkk3JvQ","operationType":"delete","parameters":{"Objects":["[MxModelReflection.Token]"]},"constants":{},"allowedUserRoleSets":[["Administrator"],["User"],["Manager"]]},{"operationId":"QnjnItKus0GhoZGUuf1edw","operationType":"callMicroflow","parameters":{"OAuthProvider":["Email_Connector.OAuthProvider"]},"constants":{"MicroflowName":"Email_Connector.OCH_OAuthProvider_SetCallbackURL_AuthCode"},"allowedUserRoleSets":[["Administrator"],["User"],["Manager"],["Guest"]]},{"operationId":"n2XPR9Z2REyOCruwcc7q4A","operationType":"rollback","parameters":{"Objects":["AnyObjectList"]},"constants":{},"allowedUserRoleSets":[["Administrator"],["User"],["Manager"],["Guest"]]},{"operationId":"tOsIMp0tM0SmJPDXli4t/g","operationType":"rollback","parameters":{"Objects":["AnyObjectList"]},"constants":{},"allowedUserRoleSets":[["Administrator"],["User"],["Manager"],["Guest"]]},{"operationId":"R51KtRtes0yRpGUYi30dvg","operationType":"callMicroflow","parameters":{"TestPattern":["MxModelReflection.TestPattern"]},"constants":{"MicroflowName":"MxModelReflection.MB_TestThePattern"},"allowedUserRoleSets":[["Administrator"],["User"],["Manager"]]},{"operationId":"+rXGNoSdIUSbOTaxfZ9/0Q","operationType":"rollback","parameters":{"Objects":["AnyObjectList"]},"constants":{},"allowedUserRoleSets":[["Administrator"],["User"],["Manager"],["Guest"]]},{"operationId":"WIw4/Gu0/kSJZ3CkiDZ7UA","operationType":"callMicroflow","parameters":{"ExampleConfiguration":["Encryption.ExampleConfiguration"]},"constants":{"MicroflowName":"Encryption.MB_SavePassword"},"allowedUserRoleSets":[]},{"operationId":"CZb4BLHpuEesmY++qKUV4g","operationType":"callMicroflow","parameters":{"EmailAccount":["Email_Connector.EmailAccount"]},"constants":{"MicroflowName":"Email_Connector.ACT_ShowAccountSettingsPage"},"allowedUserRoleSets":[["Administrator"],["Manager"]]},{"operationId":"OgJtDTON/kGIevk4+bFwAg","operationType":"rollback","parameters":{"Objects":["AnyObjectList"]},"constants":{},"allowedUserRoleSets":[["Administrator"],["User"],["Manager"],["Guest"]]},{"operationId":"srdDAbm+70aUern2cIht9Q","operationType":"callMicroflow","parameters":{"EmailAccount":["Email_Connector.EmailAccount"]},"constants":{"MicroflowName":"Email_Connector.OCH_OAuthProvider_CreateNew"},"allowedUserRoleSets":[["Administrator"],["User"],["Manager"],["Guest"]]},{"operationId":"VvYyG9UrhUq71Dk0sf7KYQ","operationType":"callMicroflow","parameters":{"OAuthProvider":["Email_Connector.OAuthProvider"]},"constants":{"MicroflowName":"Email_Connector.ACT_OAuthProvider_DeleteProvider"},"allowedUserRoleSets":[["Administrator"],["Manager"]]},{"operationId":"d5UKOXvg+0erVsH5co5yIA","operationType":"rollback","parameters":{"Objects":["AnyObjectList"]},"constants":{},"allowedUserRoleSets":[["Administrator"],["User"],["Manager"],["Guest"]]},{"operationId":"BuXbRC6/a0GMJwihtPmlIA","operationType":"callMicroflow","parameters":{"EmailAccount":["Email_Connector.EmailAccount"]},"constants":{"MicroflowName":"Email_Connector.DS_GetLDAPConfiguration"},"allowedUserRoleSets":[["Administrator"],["User"],["Manager"],["Guest"]]},{"operationId":"/qF4wnD79UelQ5vRBs6p4Q","operationType":"commit","parameters":{"Objects":["AnyObjectList"]},"constants":{},"allowedUserRoleSets":[["Administrator"],["User"],["Manager"],["Guest"]]},{"operationId":"lAsZj35FLUeA0GjyuIeRrg","operationType":"rollback","parameters":{"Objects":["AnyObjectList"]},"constants":{},"allowedUserRoleSets":[["Administrator"],["User"],["Manager"],["Guest"]]},{"operationId":"B/Pe1j/DuE+DXZwk/h4/wA","operationType":"rollback","parameters":{"Objects":["AnyObjectList"]},"constants":{},"allowedUserRoleSets":[["Administrator"],["User"],["Manager"],["Guest"]]},{"operationId":"5w+twBAbx06WeuUPl230wA","operationType":"callMicroflow","parameters":{},"constants":{"MicroflowName":"Email_Connector.ACT_OAuthProvider_Create"},"allowedUserRoleSets":[["Administrator"],["Manager"]]},{"operationId":"0/yxb2aa4U67kzQi9TVEng","operationType":"rollback","parameters":{"Objects":["AnyObjectList"]},"constants":{},"allowedUserRoleSets":[["Administrator"],["User"],["Manager"],["Guest"]]},{"operationId":"KvNJOrAUNE+HH2JHfxczvw","operationType":"callMicroflow","parameters":{"EmailProvider":["Email_Connector.EmailProvider"]},"constants":{"MicroflowName":"Email_Connector.ACT_EmailAccount_ClientCredentialsGrant_SaveAutoConfig"},"allowedUserRoleSets":[["Administrator"],["Manager"]]},{"operationId":"wm9gY7Xupkae5ktQIcdBsA","operationType":"callMicroflow","parameters":{"OutgoingServer":["Email_Connector.OutgoingServer"]},"constants":{"MicroflowName":"Email_Connector.OEN_SetOutgoingServer"},"allowedUserRoleSets":[["Administrator"],["User"],["Manager"],["Guest"]]},{"operationId":"+H5puSgaok2mxdNiJv8C0A","operationType":"rollback","parameters":{"Objects":["AnyObjectList"]},"constants":{},"allowedUserRoleSets":[["Administrator"],["User"],["Manager"],["Guest"]]},{"operationId":"FR44fy9ZbE+Efs42Lzr2cg","operationType":"callMicroflow","parameters":{"EmailAccount":["Email_Connector.EmailAccount"]},"constants":{"MicroflowName":"Email_Connector.SUB_EmailAccount_Delete"},"allowedUserRoleSets":[["Administrator"],["Manager"]]},{"operationId":"2oazeOgdmU+knn/fjv+ANQ","operationType":"callMicroflow","parameters":{"EmailMessage":["Email_Connector.EmailMessage"]},"constants":{"MicroflowName":"Email_Connector.ACT_Attachment_CreateNew"},"allowedUserRoleSets":[["Administrator"],["Manager"]]},{"operationId":"ki94CS5ugUG8PuBapjhhog","operationType":"callMicroflow","parameters":{"DbSizeEstimate":["MxModelReflection.DbSizeEstimate"]},"constants":{"MicroflowName":"MxModelReflection.OC_FindObjectType"},"allowedUserRoleSets":[["Administrator"],["User"],["Manager"],["Guest"]]},{"operationId":"mY/W8ih+wUy22mb+SBarZw","operationType":"rollback","parameters":{"Objects":["AnyObjectList"]},"constants":{},"allowedUserRoleSets":[["Administrator"],["User"],["Manager"],["Guest"]]},{"operationId":"K6IxrROEKkeEVzx+Qs18iw","operationType":"callMicroflow","parameters":{"EmailAccount":["Email_Connector.EmailAccount"]},"constants":{"MicroflowName":"Email_Connector.ACT_EmailAccount_RetrieveEmails"},"allowedUserRoleSets":[["Administrator"],["Manager"]]},{"operationId":"ZlKl/2eBhUKckLBZdLlZ+w","operationType":"rollback","parameters":{"Objects":["AnyObjectList"]},"constants":{},"allowedUserRoleSets":[["Administrator"],["User"],["Manager"],["Guest"]]},{"operationId":"nV3oeAGMh0WzFx007LBj0A","operationType":"callMicroflow","parameters":{"Token":["MxModelReflection.Token"]},"constants":{"MicroflowName":"MxModelReflection.Ch_Reference"},"allowedUserRoleSets":[["Administrator"],["User"],["Manager"],["Guest"]]},{"operationId":"Y6Rou6P240W7mk41IhHJjw","operationType":"rollback","parameters":{"Objects":["AnyObjectList"]},"constants":{},"allowedUserRoleSets":[["Administrator"],["User"],["Manager"],["Guest"]]},{"operationId":"Z7tflHDy5Ee8v+OSk+P4Lw","operationType":"commit","parameters":{"Objects":["AnyObjectList"]},"constants":{},"allowedUserRoleSets":[["Administrator"],["User"],["Manager"],["Guest"]]},{"operationId":"+vA+MtbNVUK2+1OiJjj2OQ","operationType":"rollback","parameters":{"Objects":["AnyObjectList"]},"constants":{},"allowedUserRoleSets":[["Administrator"],["User"],["Manager"],["Guest"]]},{"operationId":"HPGh9Nb/OkGBfWe0Y5Idbw","operationType":"callMicroflow","parameters":{"OAuthProvider":["Email_Connector.OAuthProvider"]},"constants":{"MicroflowName":"Email_Connector.OCH_OAuthProvider_SetCallbackURL_ClientCred"},"allowedUserRoleSets":[["Administrator"],["User"],["Manager"],["Guest"]]},{"operationId":"HleUzAtxl0alVQSOVMvsdw","operationType":"callMicroflow","parameters":{},"constants":{"MicroflowName":"MxModelReflection.IVK_RecalculateSize"},"allowedUserRoleSets":[["Administrator"],["Manager"]]},{"operationId":"fdhJ8+t1xkOdYco36iUllw","operationType":"rollback","parameters":{"Objects":["AnyObjectList"]},"constants":{},"allowedUserRoleSets":[["Administrator"],["User"],["Manager"],["Guest"]]},{"operationId":"1qMbpqks5Ey0icbRTvdFHw","operationType":"delete","parameters":{"Objects":["[MxModelReflection.Token]"]},"constants":{},"allowedUserRoleSets":[["Administrator"],["User"],["Manager"]]},{"operationId":"5Tt3KFnDK0KoiujwtgiUig","operationType":"rollback","parameters":{"Objects":["AnyObjectList"]},"constants":{},"allowedUserRoleSets":[["Administrator"],["User"],["Manager"],["Guest"]]},{"operationId":"Uh8CUU6+Zk+5mybXFmNZ8Q","operationType":"rollback","parameters":{"Objects":["AnyObjectList"]},"constants":{},"allowedUserRoleSets":[["Administrator"],["User"],["Manager"],["Guest"]]},{"operationId":"7nYuAwBX6E6TLE64S2ALug","operationType":"commit","parameters":{"Objects":["AnyObjectList"]},"constants":{},"allowedUserRoleSets":[["Administrator"],["User"],["Manager"],["Guest"]]},{"operationId":"hpmIfoM2Gk2fqyj92Saxhg","operationType":"rollback","parameters":{"Objects":["AnyObjectList"]},"constants":{},"allowedUserRoleSets":[["Administrator"],["User"],["Manager"],["Guest"]]},{"operationId":"qPc3MfBx3keMq9Jvleduzw","operationType":"callMicroflow","parameters":{"EmailProvider":["Email_Connector.EmailProvider"]},"constants":{"MicroflowName":"Email_Connector.OCH_IncomingEmailConfiguration_Select"},"allowedUserRoleSets":[["Administrator"],["User"],["Manager"],["Guest"]]},{"operationId":"reKrxwFYVUOTb8+eaFIfQg","operationType":"delete","parameters":{"Objects":["[Email_Connector.EmailMessage]"]},"constants":{},"allowedUserRoleSets":[["Administrator"],["Manager"]]},{"operationId":"uHyJ/hRM2kGGR7ovTmkuhQ","operationType":"callMicroflow","parameters":{"EmailAccount":["Email_Connector.EmailAccount"]},"constants":{"MicroflowName":"Email_Connector.ACT_EmailMessage_SendQueuedEmails"},"allowedUserRoleSets":[["Administrator"],["Manager"]]},{"operationId":"JwAoDwEWYUWvLEEq3mV/mA","operationType":"delete","parameters":{"Objects":["[Email_Connector.EmailTemplate]"]},"constants":{},"allowedUserRoleSets":[["Administrator"],["Manager"]]},{"operationId":"cK9/uegDnUeX7jPf6IlXyg","operationType":"callMicroflow","parameters":{"Token":["MxModelReflection.Token"]},"constants":{"MicroflowName":"MxModelReflection.Ch_FindObjectTypeReference"},"allowedUserRoleSets":[["Administrator"],["User"],["Manager"],["Guest"]]},{"operationId":"pnu1BD76bEOXvUnGeH8oZg","operationType":"rollback","parameters":{"Objects":["AnyObjectList"]},"constants":{},"allowedUserRoleSets":[["Administrator"],["User"],["Manager"],["Guest"]]},{"operationId":"KPQn9v6/5kuXI3Bn3H1e9g","operationType":"callMicroflow","parameters":{},"constants":{"MicroflowName":"Email_Connector.DS_EmailAccount_CreateDummyAccount"},"allowedUserRoleSets":[["Administrator"],["User"],["Manager"],["Guest"]]},{"operationId":"E/jiqxLigUy51LjSbEOVIQ","operationType":"callMicroflow","parameters":{"Registration":["UserManagement.Registration"]},"constants":{"MicroflowName":"AdministrationManagement.ACT_Request_StatusRejected"},"allowedUserRoleSets":[["Administrator"],["Manager"]]},{"operationId":"yaKTUDK5N0CZ2RcJK+baMg","operationType":"callMicroflow","parameters":{"EmailMessage":["Email_Connector.EmailMessage"]},"constants":{"MicroflowName":"Email_Connector.VAL_LDAPConfiguration"},"allowedUserRoleSets":[["Administrator"],["User"],["Manager"],["Guest"]]},{"operationId":"IZVEz80Ws0OMrO1XwMdsgA","operationType":"callMicroflow","parameters":{"EmailList":["[Email_Connector.EmailMessage]"]},"constants":{"MicroflowName":"Email_Connector.ACT_EmailMessageList_ResetQueuedStatus"},"allowedUserRoleSets":[["Administrator"],["Manager"]]},{"operationId":"Uz/QAlhG90OBYb4i38LoWw","operationType":"callMicroflow","parameters":{"EmailAccount":["Email_Connector.EmailAccount"]},"constants":{"MicroflowName":"Email_Connector.ACT_EmailAccount_ClientCredentialsGrant_SaveManualConfig"},"allowedUserRoleSets":[["Administrator"],["Manager"]]},{"operationId":"iHrIut3SA0WcX2SsqKYUsg","operationType":"callMicroflow","parameters":{"LDAPConfiguration":["Email_Connector.LDAPConfiguration"]},"constants":{"MicroflowName":"Email_Connector.DS_LDAPBaseDNList"},"allowedUserRoleSets":[["Administrator"],["User"],["Manager"],["Guest"]]},{"operationId":"3gD9B5DSnUmWZiquruvRLw","operationType":"callMicroflow","parameters":{"EmailAccount":["Email_Connector.EmailAccount"]},"constants":{"MicroflowName":"Email_Connector.ACT_EmailMessage_ComposeNewEmail"},"allowedUserRoleSets":[["Administrator"],["User"],["Manager"],["Guest"]]},{"operationId":"vIM+MRodPUa3wjiqQBFysw","operationType":"callMicroflow","parameters":{"EmailProvider":["Email_Connector.EmailProvider"]},"constants":{"MicroflowName":"Email_Connector.ACT_EmailAccount_SaveAutoConfig"},"allowedUserRoleSets":[["Administrator"],["Manager"]]},{"operationId":"WRTTW+8Hqk2+17koEVZXQw","operationType":"callMicroflow","parameters":{"AccountPasswordData":["Administration.AccountPasswordData"]},"constants":{"MicroflowName":"Administration.SaveNewAccount"},"allowedUserRoleSets":[["Administrator"],["Manager"]]},{"operationId":"c0I8xFq4UEmDOLFivxPpsA","operationType":"callMicroflow","parameters":{"EmailAccount":["Email_Connector.EmailAccount"]},"constants":{"MicroflowName":"Email_Connector.ACT_SaveEmailAccountSettingAndClosePage"},"allowedUserRoleSets":[["Administrator"],["Manager"]]},{"operationId":"5ZFTiJhMu0erTUmnddFoUA","operationType":"rollback","parameters":{"Objects":["AnyObjectList"]},"constants":{},"allowedUserRoleSets":[["Administrator"],["User"],["Manager"],["Guest"]]},{"operationId":"2JAMnzKNV02qltU7DrGVwg","operationType":"callMicroflow","parameters":{"EmailProvider":["Email_Connector.EmailProvider"]},"constants":{"MicroflowName":"Email_Connector.OCH_OutgoingEmailConfiguration_Select"},"allowedUserRoleSets":[["Administrator"],["User"],["Manager"],["Guest"]]},{"operationId":"TY/7QTN6Dk6YPlAsQDOhlA","operationType":"rollback","parameters":{"Objects":["AnyObjectList"]},"constants":{},"allowedUserRoleSets":[["Administrator"],["User"],["Manager"],["Guest"]]},{"operationId":"oMFBL1TMNUaJBVLd/MgcWg","operationType":"callMicroflow","parameters":{"Attachment":["Email_Connector.Attachment"]},"constants":{"MicroflowName":"Email_Connector.ACT_Attachment_Download"},"allowedUserRoleSets":[["Administrator"],["Manager"]]},{"operationId":"MDdkQVEvYk65dYIy8qIsqg","operationType":"rollback","parameters":{"Objects":["AnyObjectList"]},"constants":{},"allowedUserRoleSets":[["Administrator"],["User"],["Manager"],["Guest"]]},{"operationId":"ZbDBJf+2a0qVP3J67zZvEg","operationType":"callMicroflow","parameters":{},"constants":{"MicroflowName":"MxModelReflection.IVK_SyncObjects"},"allowedUserRoleSets":[["Administrator"],["Manager"]]},{"operationId":"KLCmM+soP0y0Ij2JJXpl6g","operationType":"delete","parameters":{"Objects":["[Administration.Account]"]},"constants":{},"allowedUserRoleSets":[["Administrator"],["Manager"]]},{"operationId":"GJqAMflglkybFngy/+wwig","operationType":"callMicroflow","parameters":{},"constants":{"MicroflowName":"Administration.NewWebServiceAccount"},"allowedUserRoleSets":[["Administrator"],["Manager"]]},{"operationId":"PvU2G0sbekazwvoKLGZ2Ng","operationType":"callMicroflow","parameters":{"Attachment":["Email_Connector.Attachment"]},"constants":{"MicroflowName":"Email_Connector.ACT_Attachment_Download"},"allowedUserRoleSets":[["Administrator"],["Manager"]]},{"operationId":"KruufvofUkSGoXjUhrRrpQ","operationType":"rollback","parameters":{"Objects":["AnyObjectList"]},"constants":{},"allowedUserRoleSets":[["Administrator"],["User"],["Manager"],["Guest"]]},{"operationId":"/93ybM/M5Eygdjo6xYlcpA","operationType":"rollback","parameters":{"Objects":["AnyObjectList"]},"constants":{},"allowedUserRoleSets":[["Administrator"],["User"],["Manager"],["Guest"]]},{"operationId":"CyuX6RF8XkOBJqqY3hXM0A","operationType":"delete","parameters":{"Objects":["[Encryption.PGPCertificate]"]},"constants":{},"allowedUserRoleSets":[]},{"operationId":"5Lue+pZUukGUxunmEEG14w","operationType":"rollback","parameters":{"Objects":["AnyObjectList"]},"constants":{},"allowedUserRoleSets":[["Administrator"],["User"],["Manager"],["Guest"]]},{"operationId":"kg4m3j4LzkOx+d4ZiGEuZQ","operationType":"create","parameters":{},"constants":{"ObjectType":"UserManagement.Registration"},"allowedUserRoleSets":[["Guest"]]},{"operationId":"0qkPwdPN/UqfZnh9WppALQ","operationType":"callMicroflow","parameters":{"Attachment":["Email_Connector.Attachment"]},"constants":{"MicroflowName":"Email_Connector.ACT_Attachment_Download"},"allowedUserRoleSets":[["Administrator"],["Manager"]]},{"operationId":"SM1uaskT0UWBslIYXcdauA","operationType":"callMicroflow","parameters":{"EmailTemplate":["Email_Connector.EmailTemplate"]},"constants":{"MicroflowName":"Email_Connector.ACT_EmailTemplate_ShowModelReflectionPage"},"allowedUserRoleSets":[["Administrator"],["Manager"]]},{"operationId":"ayhq94VjGkSO13mXLm3QYw","operationType":"rollback","parameters":{"Objects":["AnyObjectList"]},"constants":{},"allowedUserRoleSets":[["Administrator"],["User"],["Manager"],["Guest"]]},{"operationId":"Rf0rj6FDRU+MgWAnmcAS9Q","operationType":"callMicroflow","parameters":{"EmailTemplate":["Email_Connector.EmailTemplate"]},"constants":{"MicroflowName":"Email_Connector.ACT_EmailTemplate_Save"},"allowedUserRoleSets":[["Administrator"],["Manager"]]},{"operationId":"UQYhcKeEk0S+W1PyU+8RNg","operationType":"rollback","parameters":{"Objects":["AnyObjectList"]},"constants":{},"allowedUserRoleSets":[["Administrator"],["User"],["Manager"],["Guest"]]},{"operationId":"XY7MKUN1iEmQ+FBvzHIvwg","operationType":"callMicroflow","parameters":{"EmailMessage":["Email_Connector.EmailMessage"],"EmailAccount":["Email_Connector.EmailAccount"]},"constants":{"MicroflowName":"Email_Connector.ACT_EmailMessage_ComposeReply"},"allowedUserRoleSets":[["Administrator"],["Manager"]]},{"operationId":"6UqD53OPa06H5FB9EKcYOw","operationType":"callMicroflow","parameters":{"EmailAccount":["Email_Connector.EmailAccount"]},"constants":{"MicroflowName":"Email_Connector.OCH_Pk12Certificate_DeleteCertificate"},"allowedUserRoleSets":[["Administrator"],["User"],["Manager"],["Guest"]]},{"operationId":"JeLABJ8VxkqlIPsq32E/Aw","operationType":"create","parameters":{},"constants":{"ObjectType":"CalendarEvents.Booking"},"allowedUserRoleSets":[["Administrator"],["Manager"],["User"]]},{"operationId":"dke07GAWoEyp2hrfgAyRpw","operationType":"rollback","parameters":{"Objects":["AnyObjectList"]},"constants":{},"allowedUserRoleSets":[["Administrator"],["User"],["Manager"],["Guest"]]},{"operationId":"4/+kcjxwYkqy96P4ODex9A","operationType":"callMicroflow","parameters":{},"constants":{"MicroflowName":"System.ShowHomePage"},"allowedUserRoleSets":[["Administrator"],["User"],["Manager"],["Guest"]]},{"operationId":"V4AFc54aEkuKTz945Glgqg","operationType":"delete","parameters":{"Objects":["[Encryption.ExampleConfiguration]"]},"constants":{},"allowedUserRoleSets":[]},{"operationId":"iX1yuzJZgUqQui9iNPJ5UQ","operationType":"callMicroflow","parameters":{},"constants":{"MicroflowName":"MxModelReflection.DSL_Modules"},"allowedUserRoleSets":[["Administrator"],["User"],["Manager"],["Guest"]]},{"operationId":"xyHP+7yokki2wRWRR+rZlQ","operationType":"callMicroflow","parameters":{"EmailAccount":["Email_Connector.EmailAccount"]},"constants":{"MicroflowName":"Email_Connector.DS_GetPKCS12Certificate"},"allowedUserRoleSets":[["Administrator"],["User"],["Manager"],["Guest"]]},{"operationId":"NT4w2G2I7E68ExPWc9aRgA","operationType":"callMicroflow","parameters":{"Registration":["UserManagement.Registration"]},"constants":{"MicroflowName":"AdministrationManagement.ACT_Request_StatusApproved"},"allowedUserRoleSets":[["Administrator"],["Manager"]]},{"operationId":"iLGXifdckk+ksKlKDAJQXA","operationType":"callMicroflow","parameters":{"IncomingEmailConfiguration":["Email_Connector.IncomingEmailConfiguration"]},"constants":{"MicroflowName":"Email_Connector.DS_FolderList"},"allowedUserRoleSets":[["Administrator"],["User"],["Manager"],["Guest"]]},{"operationId":"mF+X8AWBLEu7+lH1ewS+Kw","operationType":"callMicroflow","parameters":{},"constants":{"MicroflowName":"Email_Connector.ACT_EmailAccount_LaunchEmailConnectorOverview"},"allowedUserRoleSets":[["Administrator"],["Manager"]]},{"operationId":"zilzF2CpO0aDwj36AAFMDg","operationType":"callMicroflow","parameters":{},"constants":{"MicroflowName":"MxModelReflection.IVK_SyncObjects"},"allowedUserRoleSets":[["Administrator"],["Manager"]]},{"operationId":"1BefkbR4ykm5UlVlNBBXEw","operationType":"delete","parameters":{"Objects":["[System.Session]"]},"constants":{},"allowedUserRoleSets":[["Administrator"],["User"],["Manager"],["Guest"]]},{"operationId":"xCy6REr+zkO8eLrSrEbcuw","operationType":"rollback","parameters":{"Objects":["AnyObjectList"]},"constants":{},"allowedUserRoleSets":[["Administrator"],["User"],["Manager"],["Guest"]]},{"operationId":"Etd7lOewAUeBSv3L9E+FFg","operationType":"rollback","parameters":{"Objects":["AnyObjectList"]},"constants":{},"allowedUserRoleSets":[["Administrator"],["User"],["Manager"],["Guest"]]},{"operationId":"QS35rxyafkCzj/qzGTjyqQ","operationType":"create","parameters":{},"constants":{"ObjectType":"Email_Connector.EmailTemplate"},"allowedUserRoleSets":[["Administrator"],["Manager"]]},{"operationId":"W4bvIBkLjUWZ4OYjqeJtJQ","operationType":"rollback","parameters":{"Objects":["AnyObjectList"]},"constants":{},"allowedUserRoleSets":[["Administrator"],["User"],["Manager"],["Guest"]]},{"operationId":"DaqEVZUeG0eyUl5Rm3ywmw","operationType":"rollback","parameters":{"Objects":["AnyObjectList"]},"constants":{},"allowedUserRoleSets":[["Administrator"],["User"],["Manager"],["Guest"]]},{"operationId":"h3ThSESGcUSZik4ds3RCMQ","operationType":"callMicroflow","parameters":{"Input":["RESTConsume.Input"]},"constants":{"MicroflowName":"RESTConsume.Microflow"},"allowedUserRoleSets":[["Administrator"],["User"],["Manager"],["Guest"]]},{"operationId":"OiCe4PbcJUugeFZv/AxE/w","operationType":"delete","parameters":{"Objects":["[Email_Connector.EmailMessage]"]},"constants":{},"allowedUserRoleSets":[["Administrator"],["Manager"]]},{"operationId":"GPA95Nr1QkWrzNLMX1gYRA","operationType":"rollback","parameters":{"Objects":["AnyObjectList"]},"constants":{},"allowedUserRoleSets":[["Administrator"],["User"],["Manager"],["Guest"]]},{"operationId":"p+JVjrhgiU6sI5BwrhIhjw","operationType":"create","parameters":{},"constants":{"ObjectType":"UserManagement.ProfilePicture"},"allowedUserRoleSets":[["Administrator"],["User"],["Manager"],["Guest"]]},{"operationId":"Jea4woWDm0S97re/GnbRgg","operationType":"callMicroflow","parameters":{"Folder":["Email_Connector.Folder"],"IncomingEmailConfiguration":["Email_Connector.IncomingEmailConfiguration"]},"constants":{"MicroflowName":"Email_Connector.ACT_IncomingEmailConfiguration_ChangeMoveToFolder"},"allowedUserRoleSets":[["Administrator"],["Manager"]]},{"operationId":"Wr2OVdc3YUy3D5G1Plzs+w","operationType":"create","parameters":{},"constants":{"ObjectType":"MxModelReflection.Token"},"allowedUserRoleSets":[["Administrator"],["User"],["Manager"]]},{"operationId":"QT/r9HYJTEyFXitdV6hK3A","operationType":"rollback","parameters":{"Objects":["AnyObjectList"]},"constants":{},"allowedUserRoleSets":[["Administrator"],["User"],["Manager"],["Guest"]]},{"operationId":"x0L8gQYWCk23ImfkFQyKpw","operationType":"callMicroflow","parameters":{"Token":["MxModelReflection.Token"]},"constants":{"MicroflowName":"MxModelReflection.MB_TestTokenPattern"},"allowedUserRoleSets":[["Administrator"],["User"],["Manager"]]},{"operationId":"oKMTcVD2uUGAKFkV3BMzzg","operationType":"callMicroflow","parameters":{"EmailMessage":["Email_Connector.EmailMessage"]},"constants":{"MicroflowName":"Email_Connector.VAL_LDAPConfiguration"},"allowedUserRoleSets":[["Administrator"],["User"],["Manager"],["Guest"]]},{"operationId":"e4EPiUPFlkW8CKvcZIl2lg","operationType":"rollback","parameters":{"Objects":["AnyObjectList"]},"constants":{},"allowedUserRoleSets":[["Administrator"],["User"],["Manager"],["Guest"]]},{"operationId":"ClscOPkMSkeIwi8U6Lh8LQ","operationType":"callMicroflow","parameters":{},"constants":{"MicroflowName":"Administration.RetrieveTimeZones"},"allowedUserRoleSets":[["Administrator"],["User"],["Manager"],["Guest"]]},{"operationId":"b83gnBfw2E2iVTMyMQLnog","operationType":"callMicroflow","parameters":{},"constants":{"MicroflowName":"Administration.NewAccount"},"allowedUserRoleSets":[["Administrator"],["Manager"]]},{"operationId":"rbhc+fYsc02hn4Fh3Q5m/w","operationType":"callMicroflow","parameters":{"EmailAccount":["Email_Connector.EmailAccount"]},"constants":{"MicroflowName":"Email_Connector.ACT_EmailAccount_SaveManualConfig"},"allowedUserRoleSets":[["Administrator"],["Manager"]]},{"operationId":"aWO4P3r2IUqCW6rTx7Ep+w","operationType":"delete","parameters":{"Objects":["[Email_Connector.Attachment]"]},"constants":{},"allowedUserRoleSets":[["Administrator"],["Manager"]]},{"operationId":"8Y6EvbXRpEKTKBegxKeg0g","operationType":"rollback","parameters":{"Objects":["AnyObjectList"]},"constants":{},"allowedUserRoleSets":[["Administrator"],["User"],["Manager"],["Guest"]]},{"operationId":"Az2olHN1H0Kw4uIhTGSHmw","operationType":"callMicroflow","parameters":{"EmailProvider":["Email_Connector.EmailProvider"]},"constants":{"MicroflowName":"Email_Connector.ACT_EmailAccount_SaveAutoConfig"},"allowedUserRoleSets":[["Administrator"],["Manager"]]},{"operationId":"IMXll44oXkSm1OPRPuQq+w","operationType":"rollback","parameters":{"Objects":["AnyObjectList"]},"constants":{},"allowedUserRoleSets":[["Administrator"],["User"],["Manager"],["Guest"]]},{"operationId":"KGHb3YphcUuMpIfev4PJYQ","operationType":"callMicroflow","parameters":{"OAuthProvider":["Email_Connector.OAuthProvider"]},"constants":{"MicroflowName":"Email_Connector.ACT_OAuthProvider_ShowOAuthProviderPage"},"allowedUserRoleSets":[["Administrator"],["Manager"]]},{"operationId":"D2Tt1S4AFlOacviNJ8dOVw","operationType":"callMicroflow","parameters":{"EmailAccount":["Email_Connector.EmailAccount"]},"constants":{"MicroflowName":"Email_Connector.SUB_GetOAuthURL"},"allowedUserRoleSets":[["Administrator"],["User"],["Manager"],["Guest"]]},{"operationId":"uEee23Hs1kqQSywudw+Lkg","operationType":"delete","parameters":{"Objects":["[Email_Connector.EmailMessage]"]},"constants":{},"allowedUserRoleSets":[["Administrator"],["Manager"]]},{"operationId":"jzlnPOmWzU+fvS2dgQ+vbQ","operationType":"callMicroflow","parameters":{"ExampleConfiguration":["Encryption.ExampleConfiguration"]},"constants":{"MicroflowName":"Encryption.MB_ShowChangePassword"},"allowedUserRoleSets":[]},{"operationId":"drG4L3cpckqm+9UWINMBmQ","operationType":"create","parameters":{},"constants":{"ObjectType":"CalendarEvents.Calendar"},"allowedUserRoleSets":[["Administrator"],["User"],["Manager"]]},{"operationId":"7JE6upqElUiCkpcjrHaWcw","operationType":"commit","parameters":{"Objects":["AnyObjectList"]},"constants":{},"allowedUserRoleSets":[["Administrator"],["User"],["Manager"],["Guest"]]},{"operationId":"hzqGho0om0iBMrpZGueeLA","operationType":"rollback","parameters":{"Objects":["AnyObjectList"]},"constants":{},"allowedUserRoleSets":[["Administrator"],["User"],["Manager"],["Guest"]]},{"operationId":"QbPnaQ1AzUmTIbUkapus5A","operationType":"create","parameters":{},"constants":{"ObjectType":"MxModelReflection.DbSizeEstimate"},"allowedUserRoleSets":[]},{"operationId":"+7N3KL3DXkuEr3KSwer2qQ","operationType":"rollback","parameters":{"Objects":["AnyObjectList"]},"constants":{},"allowedUserRoleSets":[["Administrator"],["User"],["Manager"],["Guest"]]},{"operationId":"6kSA2oNFYUC5Eb4vNEfFRw","operationType":"callMicroflow","parameters":{"EmailAccount":["Email_Connector.EmailAccount"]},"constants":{"MicroflowName":"Email_Connector.DS_GetPKCS12Certificate"},"allowedUserRoleSets":[["Administrator"],["User"],["Manager"],["Guest"]]},{"operationId":"PyE8/j+DPkaKmlYVd7yeDA","operationType":"callMicroflow","parameters":{"EmailTemplate":["Email_Connector.EmailTemplate"]},"constants":{"MicroflowName":"Email_Connector.DS_ModelReflectionChecker"},"allowedUserRoleSets":[["Administrator"],["User"],["Manager"],["Guest"]]},{"operationId":"ZZTEOE6UhkGNB2ARiUYgNw","operationType":"callMicroflow","parameters":{"EmailMessage":["Email_Connector.EmailMessage"]},"constants":{"MicroflowName":"Email_Connector.VAL_Pk12Certificate"},"allowedUserRoleSets":[["Administrator"],["User"],["Manager"],["Guest"]]},{"operationId":"OyjxmJXd1U+P6io+s/W3fQ","operationType":"rollback","parameters":{"Objects":["AnyObjectList"]},"constants":{},"allowedUserRoleSets":[["Administrator"],["User"],["Manager"],["Guest"]]},{"operationId":"rdhkmzKVLUyir6dAuXgyhQ","operationType":"callMicroflow","parameters":{"Equipment":["Rooms.Equipment"],"Room":["Rooms.Room"]},"constants":{"MicroflowName":"Rooms.ACT_Equipment_Save"},"allowedUserRoleSets":[["Administrator"],["Manager"]]},{"operationId":"DiNZ4aKGEEuYXGQBiMSHTw","operationType":"callMicroflow","parameters":{"Module":["MxModelReflection.Module"]},"constants":{"MicroflowName":"MxModelReflection.IVK_ToggleModule"},"allowedUserRoleSets":[["Administrator"],["User"],["Manager"],["Guest"]]},{"operationId":"nU3T7aI6aEGJzPGk+s+fow","operationType":"rollback","parameters":{"Objects":["AnyObjectList"]},"constants":{},"allowedUserRoleSets":[["Administrator"],["User"],["Manager"],["Guest"]]},{"operationId":"dKI3QxEc7EqhKXKASsjHsA","operationType":"rollback","parameters":{"Objects":["AnyObjectList"]},"constants":{},"allowedUserRoleSets":[["Administrator"],["User"],["Manager"],["Guest"]]},{"operationId":"Hl6LUa7LnESa6JrIQf5zJg","operationType":"callMicroflow","parameters":{},"constants":{"MicroflowName":"Encryption.MB_NewPrivateKey"},"allowedUserRoleSets":[]},{"operationId":"NsyUV8HHNk6HErlBe1ZN1Q","operationType":"callMicroflow","parameters":{"AccountPasswordData":["Administration.AccountPasswordData"]},"constants":{"MicroflowName":"Administration.ChangePassword"},"allowedUserRoleSets":[["Administrator"],["Manager"]]},{"operationId":"KJdiJwej5E+iEQwQaYTKcw","operationType":"callMicroflow","parameters":{"EmailAccount":["Email_Connector.EmailAccount"]},"constants":{"MicroflowName":"Email_Connector.SUB_EmailAccount_Delete"},"allowedUserRoleSets":[["Administrator"],["Manager"]]},{"operationId":"mGFdW99iaEOExcUt4efKAg","operationType":"rollback","parameters":{"Objects":["AnyObjectList"]},"constants":{},"allowedUserRoleSets":[["Administrator"],["User"],["Manager"],["Guest"]]},{"operationId":"qX+OrPUy/EGyQe7iOvABgw","operationType":"callMicroflow","parameters":{"AccountPasswordData":["Administration.AccountPasswordData"]},"constants":{"MicroflowName":"Administration.ChangeMyPassword"},"allowedUserRoleSets":[["Administrator"],["User"],["Manager"]]},{"operationId":"/prbpmjTpUSVNFK7z6AdgA","operationType":"callMicroflow","parameters":{"Certificate":["Encryption.PGPCertificate"]},"constants":{"MicroflowName":"Encryption.MB_OpenCertificateDetails"},"allowedUserRoleSets":[]},{"operationId":"xN+DrV8nnEmrTXFf7adiJw","operationType":"rollback","parameters":{"Objects":["AnyObjectList"]},"constants":{},"allowedUserRoleSets":[["Administrator"],["User"],["Manager"],["Guest"]]},{"operationId":"Bjc41fAdT0WTgB9jIRjGhg","operationType":"rollback","parameters":{"Objects":["AnyObjectList"]},"constants":{},"allowedUserRoleSets":[["Administrator"],["User"],["Manager"],["Guest"]]},{"operationId":"OUzFGOfsGEmM9BVA4ErI0A","operationType":"commit","parameters":{"Objects":["AnyObjectList"]},"constants":{},"allowedUserRoleSets":[["Administrator"],["User"],["Manager"],["Guest"]]},{"operationId":"mEpfeZs8U0CpkV2Qwf3pXA","operationType":"callMicroflow","parameters":{"EmailAccount":["Email_Connector.EmailAccount"]},"constants":{"MicroflowName":"Email_Connector.ACT_SelectedConfiguration_FetchEmailServerConfigAndShowConfigPage"},"allowedUserRoleSets":[["Administrator"],["Manager"]]},{"operationId":"qvYJAp1Ow06k362D9l738w","operationType":"rollback","parameters":{"Objects":["AnyObjectList"]},"constants":{},"allowedUserRoleSets":[["Administrator"],["User"],["Manager"],["Guest"]]},{"operationId":"rxfdwe0daUKuqMz39XO/hg","operationType":"commit","parameters":{"Objects":["AnyObjectList"]},"constants":{},"allowedUserRoleSets":[["Administrator"],["User"],["Manager"],["Guest"]]},{"operationId":"jWC4nZ1R2EeAkYLCcQk0zw","operationType":"rollback","parameters":{"Objects":["AnyObjectList"]},"constants":{},"allowedUserRoleSets":[["Administrator"],["User"],["Manager"],["Guest"]]},{"operationId":"SBFT/A/oZk698H1D1UVFRg","operationType":"callMicroflow","parameters":{"Account":["Administration.Account"]},"constants":{"MicroflowName":"Administration.ShowPasswordForm"},"allowedUserRoleSets":[["Administrator"],["Manager"]]},{"operationId":"NqBMN+p0fU6XqRmdENXtTg","operationType":"rollback","parameters":{"Objects":["AnyObjectList"]},"constants":{},"allowedUserRoleSets":[["Administrator"],["User"],["Manager"],["Guest"]]},{"operationId":"0pcBWdmev0uXOh66ZkSM+g","operationType":"commit","parameters":{"Objects":["AnyObjectList"]},"constants":{},"allowedUserRoleSets":[["Administrator"],["User"],["Manager"],["Guest"]]},{"operationId":"qCp79Ah1MUaRhh0eHSbgrw","operationType":"callMicroflow","parameters":{"Token":["MxModelReflection.Token"]},"constants":{"MicroflowName":"MxModelReflection.Ch_Member"},"allowedUserRoleSets":[["Administrator"],["User"],["Manager"],["Guest"]]},{"operationId":"vgamlm52tkG2A4QBccRaEw","operationType":"create","parameters":{},"constants":{"ObjectType":"Email_Connector.Attachment"},"allowedUserRoleSets":[["Administrator"],["Manager"]]},{"operationId":"TxHsgoU+f0CoUVftZl6YVg","operationType":"callMicroflow","parameters":{"MxObjectType":["MxModelReflection.MxObjectType"]},"constants":{"MicroflowName":"MxModelReflection.IVK_MxObjectTypeCommit"},"allowedUserRoleSets":[["Administrator"],["Manager"]]},{"operationId":"1jJeLZ2Pw0uxJJz96r13ZQ","operationType":"rollback","parameters":{"Objects":["AnyObjectList"]},"constants":{},"allowedUserRoleSets":[["Administrator"],["User"],["Manager"],["Guest"]]},{"operationId":"9HkTwY0/wUmZ5mj4PGYjiQ","operationType":"rollback","parameters":{"Objects":["AnyObjectList"]},"constants":{},"allowedUserRoleSets":[["Administrator"],["User"],["Manager"],["Guest"]]},{"operationId":"BlI2TXWMr0ymvMVnUNFNhQ","operationType":"create","parameters":{},"constants":{"ObjectType":"Encryption.ExampleConfiguration"},"allowedUserRoleSets":[]},{"operationId":"Hr3OBdCPFEi4VrhG8sd7zw","operationType":"rollback","parameters":{"Objects":["AnyObjectList"]},"constants":{},"allowedUserRoleSets":[["Administrator"],["User"],["Manager"],["Guest"]]},{"operationId":"ik2+ADL3XkGLNk3BevX8ew","operationType":"callMicroflow","parameters":{"Token":["MxModelReflection.Token"]},"constants":{"MicroflowName":"MxModelReflection.Ch_ObjectTypeStart"},"allowedUserRoleSets":[["Administrator"],["User"],["Manager"],["Guest"]]},{"operationId":"w3PPlaV340KoavuYS3TBPA","operationType":"rollback","parameters":{"Objects":["AnyObjectList"]},"constants":{},"allowedUserRoleSets":[["Administrator"],["User"],["Manager"],["Guest"]]},{"operationId":"EBdJ8ypcE0WMTUzqpr1enQ","operationType":"rollback","parameters":{"Objects":["AnyObjectList"]},"constants":{},"allowedUserRoleSets":[["Administrator"],["User"],["Manager"],["Guest"]]},{"operationId":"jBy7ktV870iCBIOYR5ybsQ","operationType":"create","parameters":{},"constants":{"ObjectType":"UserManagement.User"},"allowedUserRoleSets":[["Administrator"],["User"],["Manager"]]}]